{
  "$schema": "https://developer.microsoft.com/json-schemas/fabric/item/report/definition/visualContainer/2.6.0/schema.json",
  "name": "c907abc4351dcf8fa3e4",
  "position": {
    "x": 19.430886139907582,
    "y": 47.386363636363626,
    "z": 4000,
    "height": 26.25,
    "width": 71.25,
    "tabOrder": 51000
  },
  "visual": {
    "visualType": "textbox",
    "objects": {
      "general": [
        {
          "properties": {
            "paragraphs": [
              {
                "textRuns": [
                  {
                    "value": "Prev. Period"
                  }
                ]
              }
            ]
          }
        }
      ]
    },
    "drillFilterOtherVisuals": true
  },
  "parentGroupName": "cf1513c57fb010a8291b"
}