{
  "$schema": "https://developer.microsoft.com/json-schemas/fabric/item/report/definition/visualContainer/2.6.0/schema.json",
  "name": "efe481bf570bacf7515d",
  "position": {
    "x": 19.191577653116113,
    "y": 46.43863636363637,
    "z": 4000,
    "height": 25.724999999999998,
    "width": 71.25,
    "tabOrder": 45000
  },
  "visual": {
    "visualType": "textbox",
    "objects": {
      "general": [
        {
          "properties": {
            "paragraphs": [
              {
                "textRuns": [
                  {
                    "value": "Prev. Period"
                  }
                ]
              }
            ]
          }
        }
      ]
    },
    "drillFilterOtherVisuals": true
  },
  "parentGroupName": "675dccb9d5fe2e469df7"
}