{
  "$schema": "https://developer.microsoft.com/json-schemas/fabric/item/report/definition/visualContainer/2.6.0/schema.json",
  "name": "86868cc64b786e81963a",
  "position": {
    "x": 0,
    "y": 0,
    "z": 0,
    "height": 400,
    "width": 1180,
    "tabOrder": 84000
  },
  "visual": {
    "visualType": "basicShape",
    "objects": {
      "general": [
        {
          "properties": {
            "shapeType": {
              "expr": {
                "Literal": {
                  "Value": "'rectangle'"
                }
              }
            }
          }
        }
      ],
      "fill": [
        {
          "properties": {
            "show": {
              "expr": {
                "Literal": {
                  "Value": "false"
                }
              }
            }
          }
        }
      ],
      "line": [
        {
          "properties": {
            "weight": {
              "expr": {
                "Literal": {
                  "Value": "0D"
                }
              }
            }
          }
        }
      ]
    },
    "visualContainerObjects": {
      "background": [
        {
          "properties": {
            "show": {
              "expr": {
                "Literal": {
                  "Value": "true"
                }
              }
            },
            "transparency": {
              "expr": {
                "Literal": {
                  "Value": "0D"
                }
              }
            },
            "color": {
              "solid": {
                "color": {
                  "expr": {
                    "Literal": {
                      "Value": "'#002A29'"
                    }
                  }
                }
              }
            }
          }
        }
      ],
      "border": [
        {
          "properties": {
            "show": {
              "expr": {
                "Literal": {
                  "Value": "true"
                }
              }
            },
            "radius": {
              "expr": {
                "Literal": {
                  "Value": "4D"
                }
              }
            },
            "color": {
              "solid": {
                "color": {
                  "expr": {
                    "Literal": {
                      "Value": "'#002A29'"
                    }
                  }
                }
              }
            }
          }
        }
      ],
      "dropShadow": [
        {
          "properties": {
            "show": {
              "expr": {
                "Literal": {
                  "Value": "false"
                }
              }
            },
            "color": {
              "solid": {
                "color": {
                  "expr": {
                    "Literal": {
                      "Value": "'#EDEDED'"
                    }
                  }
                }
              }
            },
            "preset": {
              "expr": {
                "Literal": {
                  "Value": "'Center'"
                }
              }
            },
            "angle": {
              "expr": {
                "Literal": {
                  "Value": "0L"
                }
              }
            },
            "shadowDistance": {
              "expr": {
                "Literal": {
                  "Value": "0L"
                }
              }
            },
            "shadowBlur": {
              "expr": {
                "Literal": {
                  "Value": "15L"
                }
              }
            },
            "shadowSpread": {
              "expr": {
                "Literal": {
                  "Value": "3L"
                }
              }
            },
            "transparency": {
              "expr": {
                "Literal": {
                  "Value": "70L"
                }
              }
            }
          }
        }
      ],
      "visualHeader": [
        {
          "properties": {
            "show": {
              "expr": {
                "Literal": {
                  "Value": "false"
                }
              }
            }
          }
        }
      ],
      "general": [
        {
          "properties": {
            "keepLayerOrder": {
              "expr": {
                "Literal": {
                  "Value": "true"
                }
              }
            }
          }
        }
      ]
    },
    "drillFilterOtherVisuals": true
  },
  "parentGroupName": "c4b9466f4a0520a5ae80"
}